README.md
setup.py
mftool/__init__.py
mftool/const.json
mftool/mftool.py
mftool/utils.py
mftool.egg-info/PKG-INFO
mftool.egg-info/SOURCES.txt
mftool.egg-info/dependency_links.txt
mftool.egg-info/requires.txt
mftool.egg-info/top_level.txt