Metadata-Version: 2.1
Name: mftool
Version: 3.0
Summary: Library for getting real time Mutual funds info
Home-page: https://github.com/NayakwadiS/mftool
Author: SujitN
Author-email: nayakwadi_sujit@rediffmail.com
License: MIT
Keywords: amfi,quote,mutual-funds,funds,bse,nse,market,stock,stocks
Platform: UNKNOWN
